HISTORY.txt
LICENSE
MANIFEST.in
README.md
requirements.txt
setup.cfg
setup.py
rcsb/__init__.py
rcsb.utils.dssp.egg-info/PKG-INFO
rcsb.utils.dssp.egg-info/SOURCES.txt
rcsb.utils.dssp.egg-info/dependency_links.txt
rcsb.utils.dssp.egg-info/not-zip-safe
rcsb.utils.dssp.egg-info/requires.txt
rcsb.utils.dssp.egg-info/top_level.txt
rcsb/utils/__init__.py
rcsb/utils/dssp/__init__.py