Metadata-Version: 2.1
Name: rcsb.utils.dssp
Version: 0.11
Summary: RCSB Python DSSP Utilities
Home-page: https://github.com/rcsb/py-rcsb_utils_dssp
Author: Dennis Piehl
Author-email: dennis.piehl@rcsb.org
License: Apache 2.0
Classifier: Development Status :: 3 - Alpha
Classifier: Intended Audience :: Developers
Classifier: Natural Language :: English
Classifier: License :: OSI Approved :: Apache Software License
Classifier: Programming Language :: Python
Classifier: Programming Language :: Python :: 3
Classifier: Programming Language :: Python :: 3.9
Provides-Extra: dev
Provides-Extra: test
License-File: LICENSE
